kernels/CosineSimilarityKernel.py
kernels/FourierKernel.py
kernels/LinearKernel.py
kernels/PolynomialKernel.py
kernels/RBFKernel.py
kernels/SplineKernel.py
kernels/__init__.py
kernels/cosine_similarity_kernel.py
kernels/fourier_kernel.py
kernels/linear_kernel.py
kernels/polynomial_kernel.py
kernels/rbf_kernel.py
kernels/spline_kernel.py
kernels/base/__init__.py
kernels/base/base_kernel.py
kernels/experimental/__init__.py
kernels/experimental/p_spectrum_kernel.py
kernels/utils/__init__.py
kernels/utils/utils.py
tensorflow_kernels-0.1.2.dist-info/LICENSE
tensorflow_kernels-0.1.2.dist-info/METADATA
tensorflow_kernels-0.1.2.dist-info/WHEEL
tensorflow_kernels-0.1.2.dist-info/top_level.txt
tensorflow_kernels-0.1.2.dist-info/RECORD
