Metadata-Version: 2.1
Name: tensorflow-kernels
Version: 0.1.2
Summary: A package with Tensorflow (both CPU and GPU) implementation of most popular Kernels for kernels methods (SVM, MKL...).
Home-page: https://github.com/sirCamp/tensorflow-kernels
Author: Campese Stefano
Author-email: stefano.campese.90@gmail.com
License: MIT
Platform: UNKNOWN
Classifier: Development Status :: 3 - Alpha
Classifier: Programming Language :: Python :: 3.6
Classifier: Programming Language :: Python :: 2.7
Classifier: Topic :: Scientific/Engineering :: Artificial Intelligence
Classifier: Topic :: Scientific/Engineering :: Mathematics
Classifier: License :: OSI Approved :: MIT License
Classifier: Operating System :: OS Independent
Requires-Dist: tensorflow
Requires-Dist: numpy
